egsnrc_dosxyz/__init__.py
egsnrc_dosxyz/dcm2egs_3ddose.py
egsnrc_dosxyz/dcm2egs_angles.py
egsnrc_dosxyz/dose3d2vtr.py
egsnrc_dosxyz/egs3ddose.py
egsnrc_dosxyz/egsphant.py
egsnrc_dosxyz/iaeaphsp_header.py
egsnrc_dosxyz-0.0.4.dist-info/LICENSE
egsnrc_dosxyz-0.0.4.dist-info/METADATA
egsnrc_dosxyz-0.0.4.dist-info/WHEEL
egsnrc_dosxyz-0.0.4.dist-info/top_level.txt
egsnrc_dosxyz-0.0.4.dist-info/RECORD
